[
    {
        "id": "0-0",
        "open": "true",
        "subnodes": [
            {
                "id": "0-0-0",
                "open": "true",
                "subnodes": [
                    {
                        "id": "0-0-0-0",
                        "open": "false",
                        "name": "管理員管理",
                        "url": "listAdmin.action"
                    },
                    {
                        "id": "0-0-0-1",
                        "open": "false",
                        "name": "角色管理",
                        "url": "listRole.action"
                    },
                    {
                        "id": "0-0-0-2",
                        "open": "false",
                        "name": "權限資源管理",
                        "url": "listPurview.action"
                    },
                    {
                        "id": "0-0-0-3",
                        "open": "false",
                        "name": "日誌查詢",
                        "url": "listSysAdminLog.action"
                    },
                    {
                        "id": "0-0-0-4",
                        "open": "false",
                        "name": "工作流查詢",
                        "url": "listSysWorkflow.action"
                    }
                ],
                "name": "系統管理模組"
            },
            {
                "id": "0-0-1",
                "subnodes": [
                    {
                        "id": "0-0-1-0",
                        "open": "false",
                        "subnodes": [
                            {
                                "id": "0-0-1-0-0",
                                "open": "false",
                                "name": "電視",
                                "roles": {},
                                "url": "listUiPageSkin.action?device=1"
                            },
                            {
                                "id": "0-0-1-0-1",
                                "open": "false",
                                "name": "平板電腦",
                                "url": "listUiPageSkin.action?device=2"
                            },
                            {
                                "id": "0-0-1-0-2",
                                "open": "false",
                                "name": "智能手機",
                                "url": "listUiPageSkin.action?device=3"
                            },
                            {
                                "id": "0-0-1-0-3",
                                "open": "false",
                                "name": "智能穿帶設備",
                                "url": "listUiPageSkin.action?device=4"
                            }
                        ],
                        "name": "版面管理"
                    },
                    {
                        "id": "0-0-1-1",
                        "open": "false",
                        "subnodes": [
                            {
                                "id": "0-0-1-1-0",
                                "open": "false",
                                "name": "電視",
                                "url": "listUiPageChannel.action?device=1"
                            },
                            {
                                "id": "0-0-1-1-1",
                                "open": "false",
                                "name": "平板電腦",
                                "url": "listUiPageChannel.action?device=2"
                            },
                            {
                                "id": "0-0-1-1-2",
                                "open": "false",
                                "name": "智能手機",
                                "url": "listUiPageChannel.action?device=3"
                            },
                            {
                                "id": "0-0-1-1-3",
                                "open": "false",
                                "name": "智能穿戴設備",
                                "url": "listUiPageChannel.action?device=4"
                            }
                        ],
                        "name": "頻道管理"
                    },
                    {
                        "id": "0-0-1-2",
                        "open": "false",
                        "subnodes": [
                            {
                                "id": "0-0-1-2-0",
                                "open": "false",
                                "name": "桌面設定",
                                "url": "listDeskSetting.action"
                            }
                        ],
                        "name": "設定"
                    }
                ],
                "name": "UI管理模組"
            },
            {
                "id": "0-0-2",
                "subnodes": [
                    {
                        "id": "0-0-2-0",
                        "open": "false",
                        "subnodes": [
                            {
                                "id": "0-0-2-0-0",
                                "open": "false",
                                "name": "設備管理",
                                "url": "listDevice.action"
                            },
                            {
                                "id": "0-0-2-0-1",
                                "open": "false",
                                "name": "操作系统更新",
                                "url": "listOs.action"
                            },
                            {
                                "id": "0-0-2-0-2",
                                "open": "false",
                                "name": "操作系统資源更新",
                                "url": "listOsResources.action"
                            }
                        ],
                        "name": "操作系統管理"
                    },
                    {
                        "id": "0-0-2-1",
                        "open": "false",
                        "subnodes": [
                            {
                                "id": "0-0-2-1-0",
                                "open": "false",
                                "name": "APP更新統計",
                                "url": "listAppStatistics.action"
                            },
                            {
                                "id": "0-0-2-1-1",
                                "open": "false",
                                "name": "系统更新統計",
                                "url": "listOsStatistics.action"
                            }
                        ],
                        "name": "OTA統計"
                    }
                ],
                "name": "OTA管理模組"
            },
            {
                "id": "0-0-3",
                "open": "false",
                "subnodes": [
                    {
                        "id": "0-0-3-0",
                        "open": "false",
                        "subnodes": [
                            {
                                "id": "0-0-3-0-0",
                                "open": "false",
                                "name": "普通用户",
                                "url": "htgetlistDevUserManage.action"
                            },
                            {
                                "id": "0-0-3-0-1",
                                "open": "false",
                                "name": "開發者用戶",
                                "url": "htgetlistDevUserinfoManage.action"
                            }
                        ],
                        "name": "開發者用戶管理"
                    },
                    {
                        "id": "0-0-3-1",
                        "open": "false",
                        "subnodes": [
                            {
                                "id": "0-0-3-1-0",
                                "open": "false",
                                "name": "待審核應用",
                                "url": "listDevTvApp.action?httpappstate=0"
                            },
                            {
                                "id": "0-0-3-1-1",
                                "open": "false",
                                "name": "未通過審核應用",
                                "url": "listDevTvApp.action?httpappstate=2"
                            },
                            {
                                "id": "0-0-3-1-2",
                                "open": "false",
                                "name": "已審核應用",
                                "url": "listDevTvApp.action?httpappstate=1"
                            }
                        ],
                        "name": "TV應用管理"
                    },
                    {
                        "id": "0-0-3-2",
                        "open": "false",
                        "subnodes": [
                            {
                                "id": "0-0-3-2-0",
                                "open": "false",
                                "name": "待審核應用",
                                "url": "htgetlistDevMobileAppHT.action?httpappstate=0"
                            },
                            {
                                "id": "0-0-3-2-1",
                                "open": "false",
                                "name": "未通過審核應用",
                                "url": "htgetlistDevMobileAppHT.action?httpappstate=2"
                            },
                            {
                                "id": "0-0-3-2-2",
                                "open": "false",
                                "name": "已審核應用",
                                "url": "htgetlistDevMobileAppHT.action?httpappstate=1"
                            }
                        ],
                        "name": "移動應用管理"
                    },
                    {
                        "id": "0-0-3-3",
                        "open": "false",
                        "subnodes": [
                            {
                                "id": "0-0-3-3-0",
                                "open": "false",
                                "name": "待審核應用",
                                "url": "htgetlistDevWebAppHT.action?httpappstate=0"
                            },
                            {
                                "id": "0-0-3-3-1",
                                "open": "false",
                                "name": "未通過審核應用",
                                "url": "htgetlistDevWebAppHT.action?httpappstate=2"
                            },
                            {
                                "id": "0-0-3-3-2",
                                "open": "false",
                                "name": "已審核應用",
                                "url": "htgetlistDevWebAppHT.action?httpappstate=1"
                            }
                        ],
                        "name": "WEB應用管理"
                    },
                    {
                        "id": "0-0-3-4",
                        "open": "false",
                        "subnodes": [
                            {
                                "id": "0-0-3-4-0",
                                "open": "false",
                                "name": "待審核應用",
                                "url": "htgetlistDevResourceHT.action?appstate=0"
                            },
                            {
                                "id": "0-0-3-4-1",
                                "open": "false",
                                "name": "未通過審核應用",
                                "url": "htgetlistDevResourceHT.action?appstate=2"
                            },
                            {
                                "id": "0-0-3-4-2",
                                "open": "false",
                                "name": "已審核應用",
                                "url": "htgetlistDevResourceHT.action?appstate=1"
                            },
                            {
                                "id": "0-0-3-4-3",
                                "open": "false",
                                "name": "未提交應用",
                                "url": "htgetlistDevResourceHT.action?appstate=-1"
                            }
                        ],
                        "name": "資源管理"
                    }
                ],
                "name": "APP開發者中心"
            },
            {
                "id": "0-0-4",
                "open": "false",
                "subnodes": [
                    {
                        "id": "0-0-4-0",
                        "open": "false",
                        "name": "分類管理",
                        "url": "listAppType.action"
                    },
                    {
                        "id": "0-0-4-1",
                        "open": "false",
                        "subnodes": [
                            {
                                "id": "0-0-4-1-0",
                                "open": "false",
                                "subnodes": [
                                    {
                                        "id": "0-0-4-1-0-0",
                                        "open": "false",
                                        "name": "待審核",
                                        "url": "listPendingManagedTvApp.action"
                                    },
                                    {
                                        "id": "0-0-4-1-0-1",
                                        "open": "false",
                                        "name": "已上架",
                                        "url": "listOnShelfManagedTvApp.action"
                                    },
                                    {
                                        "id": "0-0-4-1-0-2",
                                        "open": "false",
                                        "name": "已下架",
                                        "url": "listOffShelfManagedTvApp.action"
                                    }
                                ],
                                "name": "應用"
                            },
                            {
                                "id": "0-0-4-1-1",
                                "open": "false",
                                "subnodes": [
                                    {
                                        "id": "0-0-4-1-1-0",
                                        "open": "false",
                                        "name": "欄目管理",
                                        "url": "management/platform/app/tv/column/column_list_tree.jsp"
                                    },
                                    {
                                        "id": "0-0-4-1-1-1",
                                        "open": "false",
                                        "name": "內容管理",
                                        "url": "management/platform/app/tv/content/tree.jsp"
                                    }
                                ],
                                "name": "欄目"
                            }
                        ],
                        "name": "TV應用管理"
                    }
                ],
                "name": "APP管理模組"
            },
            {
                "id": "0-0-5",
                "open": "true",
                "subnodes": [
                    {
                        "id": "0-0-5-0",
                        "open": "false",
                        "subnodes": [
                            {
                                "id": "0-0-5-0-0",
                                "open": "false",
                                "name": "待辦事項",
                                "url": "listSysAuditTask.action"
                            },
                            {
                                "id": "0-0-5-0-1",
                                "open": "false",
                                "name": "已辦事項",
                                "url": "listCompletSysAuditTask.action"
                            }
                        ],
                        "name": "UI管理模组"
                    }
                ],
                "name": "辦理事項"
            }, {"id": "0-0-6","open": "true","name": "愛唱內容管理", "subnodes": [{ "id": "0-0-6-0","open": "false", "name": "隨意聽管理"},{ "id": "0-0-6-1", "open": "false","name": "雲端K歌"} ,{"id": "0-0-6-2","open": "false","name": "雲端PK"}]}
        ],
        "name": "OSP系统管理中心"
    }
]